llm_exa.py
llm_exa-0.1.0.dist-info/licenses/LICENSE
llm_exa-0.1.0.dist-info/METADATA
llm_exa-0.1.0.dist-info/WHEEL
llm_exa-0.1.0.dist-info/entry_points.txt
llm_exa-0.1.0.dist-info/top_level.txt
llm_exa-0.1.0.dist-info/RECORD
