Metadata-Version: 2.4
Name: llm-exa
Version: 0.1.0
Summary: LLM plugin for accessing Exa.ai API
Author: Nico Bailon
License: Apache-2.0
Project-URL: Homepage, https://github.com/nicobailon/llm-exa
Project-URL: Issues, https://github.com/nicobailon/llm-exa/issues
Classifier: License :: OSI Approved :: Apache Software License
License-File: LICENSE
Requires-Dist: llm
Requires-Dist: requests
Provides-Extra: test
Requires-Dist: pytest; extra == "test"
Requires-Dist: pytest-cov; extra == "test"
Dynamic: license-file
